CHANGES.txt
LICENSE.txt
MANIFEST.in
README.rst
setup.py
js/__init__.py
js.trix.egg-info/PKG-INFO
js.trix.egg-info/SOURCES.txt
js.trix.egg-info/dependency_links.txt
js.trix.egg-info/entry_points.txt
js.trix.egg-info/namespace_packages.txt
js.trix.egg-info/not-zip-safe
js.trix.egg-info/requires.txt
js.trix.egg-info/top_level.txt
js/trix/__init__.py
js/trix/test_trix.txt
js/trix/resources/trix.css
js/trix/resources/trix.js