Metadata-Version: 1.1
Name: js.trix
Version: 1.3.0
Summary: Fanstatic packaging of Trix
Home-page: https://github.com/minddistrict/js.trix
Author: UNKNOWN
Author-email: UNKNOWN
License: MIT
Platform: UNKNOWN
Classifier: Programming Language :: Python :: 2.6
Classifier: Programming Language :: Python :: 2.7
Classifier: Programming Language :: Python :: 3.2
Classifier: Programming Language :: Python :: Implementation :: PyPy
